[
    { "title": "在風裡奔跑的名字", "artist": "皮皮", "tags": ["皮皮原創","J-Pop"] },
    { "title": "靠近你的節奏", "artist": "皮皮", "tags": ["皮皮原創","J-Pop"] },
    { "title": "奔向光的那一刻", "artist": "皮皮", "tags": ["皮皮原創","J-Pop"] },
    { "title": "校園淡影", "artist": "皮皮", "tags": ["皮皮原創","J-Pop"] },
    { "title": "訊號同步", "artist": "皮皮", "tags": ["皮皮原創","J-Pop"] },
    { "title": "追光的瞬間", "artist": "皮皮", "tags": ["皮皮原創","J-Pop"] },
    { "title": "傾聽的距離", "artist": "皮皮", "tags": ["皮皮原創","J-Pop"] },
    { "title": "想大聲說出來", "artist": "皮皮", "tags": ["皮皮原創","J-Pop"] },
    { "title": "影中之心", "artist": "皮皮", "tags": ["皮皮原創","J-Pop"] }
]
